vidtracker/__init__.py
vidtracker/cli.py
vidtracker/dfs.py
vidtracker/lk.py
vidtracker/mil.py
vidtracker/util.py
vidtracker/video.py
vidtracker-0.1.4.dist-info/LICENSE
vidtracker-0.1.4.dist-info/METADATA
vidtracker-0.1.4.dist-info/WHEEL
vidtracker-0.1.4.dist-info/entry_points.txt
vidtracker-0.1.4.dist-info/top_level.txt
vidtracker-0.1.4.dist-info/RECORD
