Metadata-Version: 2.1
Name: vidtracker
Version: 0.1.4
Summary: Video Object Tracking Toolkit
Author-email: Keyne Oei <keynekassapa13@gmail.com>
License: MIT License
Requires-Python: >=3.8
License-File: LICENSE
Requires-Dist: contourpy >=1.1.1
Requires-Dist: cycler >=0.12.1
Requires-Dist: fonttools >=4.57.0
Requires-Dist: importlib-resources >=6.4.5
Requires-Dist: kiwisolver >=1.4.7
Requires-Dist: loguru >=0.7.3
Requires-Dist: matplotlib >=3.7.5
Requires-Dist: numpy >=1.24.4
Requires-Dist: opencv-python >=4.11.0.86
Requires-Dist: packaging >=25.0
Requires-Dist: pillow >=10.4.0
Requires-Dist: pyparsing >=3.1.4
Requires-Dist: python-box >=7.2.0
Requires-Dist: python-dateutil >=2.9.0.post0
Requires-Dist: six >=1.17.0
Requires-Dist: zipp >=3.20.2
Requires-Dist: scikit-learn
